sims_slack_bot/__init__.py
sims_slack_bot/_bot.py
sims_slack_bot-0.1.0.dist-info/LICENSE
sims_slack_bot-0.1.0.dist-info/METADATA
sims_slack_bot-0.1.0.dist-info/WHEEL
sims_slack_bot-0.1.0.dist-info/top_level.txt
sims_slack_bot-0.1.0.dist-info/RECORD
