Metadata-Version: 2.2
Name: sims_slack_bot
Version: 0.1.0
Summary: A simple Slack bot for sending messages to channels and users
Author-email: Josu <josue.curto@gmail.com>
Project-URL: Homepage, https://github.com/Josuerinho/slack_bot.git
Classifier: Programming Language :: Python :: 3
Classifier: License :: OSI Approved :: MIT License
Classifier: Operating System :: OS Independent
Requires-Python: >=3.6
License-File: LICENSE
Requires-Dist: slack-bolt<2.0.0,>=1.21.3
Provides-Extra: dev
Requires-Dist: build>=0.9.0; extra == "dev"
Requires-Dist: twine>=3.8.0; extra == "dev"
